scc_firewall_manager_sdk/__init__.py
scc_firewall_manager_sdk/api_client.py
scc_firewall_manager_sdk/api_response.py
scc_firewall_manager_sdk/configuration.py
scc_firewall_manager_sdk/exceptions.py
scc_firewall_manager_sdk/py.typed
scc_firewall_manager_sdk/rest.py
scc_firewall_manager_sdk/api/__init__.py
scc_firewall_manager_sdk/api/ai_assistant_api.py
scc_firewall_manager_sdk/api/asa_access_groups_api.py
scc_firewall_manager_sdk/api/asa_access_rules_api.py
scc_firewall_manager_sdk/api/asa_interfaces_api.py
scc_firewall_manager_sdk/api/audit_logs_api.py
scc_firewall_manager_sdk/api/change_requests_api.py
scc_firewall_manager_sdk/api/changelogs_api.py
scc_firewall_manager_sdk/api/command_line_interface_api.py
scc_firewall_manager_sdk/api/commands_api.py
scc_firewall_manager_sdk/api/connectors_api.py
scc_firewall_manager_sdk/api/device_health_aggregations_api.py
scc_firewall_manager_sdk/api/device_health_api.py
scc_firewall_manager_sdk/api/device_upgrades_api.py
scc_firewall_manager_sdk/api/events_api.py
scc_firewall_manager_sdk/api/interface_health_aggregations_api.py
scc_firewall_manager_sdk/api/inventory_api.py
scc_firewall_manager_sdk/api/licensing_api.py
scc_firewall_manager_sdk/api/meta_api.py
scc_firewall_manager_sdk/api/msp_device_upgrades_api.py
scc_firewall_manager_sdk/api/msp_inventory_api.py
scc_firewall_manager_sdk/api/msp_licensing_api.py
scc_firewall_manager_sdk/api/msp_tenant_management_api.py
scc_firewall_manager_sdk/api/msp_user_management_api.py
scc_firewall_manager_sdk/api/object_management_api.py
scc_firewall_manager_sdk/api/remote_access_monitoring_api.py
scc_firewall_manager_sdk/api/search_api.py
scc_firewall_manager_sdk/api/tenant_management_api.py
scc_firewall_manager_sdk/api/transactions_api.py
scc_firewall_manager_sdk/api/users_api.py
scc_firewall_manager_sdk/models/__init__.py
scc_firewall_manager_sdk/models/access_group.py
scc_firewall_manager_sdk/models/access_group_create_input.py
scc_firewall_manager_sdk/models/access_group_page.py
scc_firewall_manager_sdk-1.15.981.dist-info/METADATA
scc_firewall_manager_sdk-1.15.981.dist-info/WHEEL
scc_firewall_manager_sdk-1.15.981.dist-info/top_level.txt
scc_firewall_manager_sdk-1.15.981.dist-info/RECORD
