Metadata-Version: 2.1
Name: scc-firewall-manager-sdk
Version: 1.15.981
Summary: Cisco Security Cloud Control Firewall Manager API
Home-page: 
Author: Cisco Security Cloud Control TAC
Author-email: cdo.tac@cisco.com
Project-URL: Documentation, https://scc-firewall-manager-sdk.readthedocs.io/
Keywords: OpenAPI,OpenAPI-Generator,Cisco Security Cloud Control Firewall Manager API
Requires-Dist: pydantic (>=2)
Requires-Dist: python-dateutil
Requires-Dist: typing-extensions (>=4.7.1)
Requires-Dist: urllib3 (<2.1.0,>=1.25.3)
